agentpayy/__init__.py
agentpayy/crewai.py
agentpayy/langchain.py
agentpayy-1.0.2.dist-info/METADATA
agentpayy-1.0.2.dist-info/WHEEL
agentpayy-1.0.2.dist-info/top_level.txt
agentpayy-1.0.2.dist-info/RECORD
