Metadata-Version: 2.4
Name: agentpayy
Version: 1.0.2
Summary: AgentPayyKit Python SDK - Pay-per-call APIs for AI agents
Home-page: https://github.com/AgentPayy/agentpayy
Author: AgentPayyKit Team
Keywords: ai agents payments crypto ethereum web3 api monetization
Classifier: Development Status :: 4 - Beta
Classifier: Intended Audience :: Developers
Classifier: License :: OSI Approved :: MIT License
Classifier: Programming Language :: Python :: 3.8
Classifier: Programming Language :: Python :: 3.9
Classifier: Programming Language :: Python :: 3.10
Classifier: Programming Language :: Python :: 3.11
Requires-Python: >=3.8
Requires-Dist: web3>=6.0.0
Requires-Dist: requests>=2.28.0
Requires-Dist: eth-account>=0.9.0
Requires-Dist: pydantic>=2.0.0
Provides-Extra: crewai
Requires-Dist: crewai>=0.1.0; extra == "crewai"
Provides-Extra: langchain
Requires-Dist: langchain>=0.1.0; extra == "langchain"
Provides-Extra: dev
Requires-Dist: pytest>=7.0.0; extra == "dev"
Requires-Dist: black>=23.0.0; extra == "dev"
Dynamic: author
Dynamic: classifier
Dynamic: description
Dynamic: description-content-type
Dynamic: home-page
Dynamic: keywords
Dynamic: provides-extra
Dynamic: requires-dist
Dynamic: requires-python
Dynamic: summary
